pycomm_scanlist/__init__.py
pycomm_scanlist/event.py
pycomm_scanlist/plc.py
pycomm_scanlist/scanlist.py
pycomm_scanlist/tag.py
pycomm_scanlist-0.1.dist-info/METADATA
pycomm_scanlist-0.1.dist-info/RECORD
pycomm_scanlist-0.1.dist-info/WHEEL
pycomm_scanlist-0.1.dist-info/top_level.txt
