Metadata-Version: 2.1
Name: pycomm-scanlist
Version: 0.1
Summary: UNKNOWN
Home-page: https://github.com/patrickjmcd/pycomm-scanlist
Author: Patrick McDonagh
Author-email: patrickjmcd@gmail.com
License: GNU General Public License v3.0
Platform: UNKNOWN
Requires-Dist: pycomm
